blazon/__init__.py
blazon/constraints/__init__.py
blazon/constraints/base.py
blazon/constraints/conditionals.py
blazon/constraints/containers.py
blazon/constraints/formats.py
blazon/constraints/maps.py
blazon/constraints/numbers.py
blazon/constraints/strings.py
blazon/environment.py
blazon/environments/__init__.py
blazon/environments/json_schema.py
blazon/helpers.py
blazon/schema.py
blazon/schematic.py
blazon-0.1.0b0.dist-info/WHEEL
blazon-0.1.0b0.dist-info/METADATA
blazon-0.1.0b0.dist-info/RECORD
